monocle_partners-0.2.0.2.dist-info/metadata.json
monocle_partners-0.2.0.2.dist-info/WHEEL
monocle_partners-0.2.0.2.dist-info/METADATA
monocle_partners-0.2.0.2.dist-info/top_level.txt
monocle_partners-0.2.0.2.dist-info/DESCRIPTION.rst
monocle_partners-0.2.0.2.dist-info/RECORD
monocle_partners/__init__.py
monocle_partners/models.py
monocle_partners/monocle.py
monocle_partners/admin.py
monocle_partners/templates/monocle_partners/monocle_partners.html
monocle_partners/fixtures/monocle_partners.json
monocle_partners/fixtures/monocle_partners/sqlite-logo.png
monocle_partners/fixtures/monocle_partners/partner_6.gif
monocle_partners/fixtures/monocle_partners/partner_2.gif
monocle_partners/fixtures/monocle_partners/mysql.jpg
monocle_partners/fixtures/monocle_partners/partner_4.gif
monocle_partners/fixtures/monocle_partners/partner_7.gif
monocle_partners/fixtures/monocle_partners/postgresql.png
monocle_partners/fixtures/monocle_partners/partner_6.png
monocle_partners/fixtures/monocle_partners/Tulips.jpg
monocle_partners/fixtures/monocle_partners/partner_1.gif
monocle_partners/fixtures/monocle_partners/partner_5.gif
monocle_partners/fixtures/monocle_partners/python.png
monocle_partners/static/monocle_partners/monocle_partners.css
monocle_partners/static/monocle_partners/monocle_partners.js
